sl2pm/__init__.py
sl2pm/__main__.py
sl2pm/bistable_bias.py
sl2pm/misc.py
sl2pm/models.py
sl2pm/pmt.py
sl2pm/track_qd.py
sl2pm/track_rbc.py
sl2pm/track_vessel.py
sl2pm/__pycache__/__init__.cpython-312.pyc
sl2pm/__pycache__/__main__.cpython-312.pyc
sl2pm/__pycache__/bistable_bias.cpython-312.pyc
sl2pm/__pycache__/misc.cpython-312.pyc
sl2pm/__pycache__/models.cpython-312.pyc
sl2pm/__pycache__/pmt.cpython-312.pyc
sl2pm/__pycache__/sl2pm.cpython-312.pyc
sl2pm/__pycache__/track_qd.cpython-312.pyc
sl2pm/__pycache__/track_rbc.cpython-312.pyc
sl2pm/__pycache__/track_vessel.cpython-312.pyc
sl2pm-1.0.1.dist-info/LICENSE
sl2pm-1.0.1.dist-info/METADATA
sl2pm-1.0.1.dist-info/WHEEL
sl2pm-1.0.1.dist-info/entry_points.txt
sl2pm-1.0.1.dist-info/top_level.txt
sl2pm-1.0.1.dist-info/RECORD
