Metadata-Version: 2.1
Name: sl2pm
Version: 1.0.1
Summary: Tracking of nanoparticles, red blood cells, and microvessel walls with super-localization two-photon microscopy (SL2PM)
Author-email: Nikolay Kutuzov <kutuzovnp@gmail.com>
Project-URL: Bug Tracker, https://github.com/drkutuzov/sl2pm/issues
Project-URL: Homepage, https://github.com/drkutuzov/sl2pm
Classifier: Programming Language :: Python :: 3
Classifier: License :: OSI Approved :: MIT License
Classifier: Operating System :: OS Independent
Requires-Python: >=3.9
License-File: LICENSE
Requires-Dist: numpy ==1.26.3
Requires-Dist: matplotlib ==3.8.2
Requires-Dist: scipy ==1.12.0
Requires-Dist: mpmath ==1.3.0
Requires-Dist: jupyterlab ==4.0.12
Requires-Dist: notebook ==7.0.7
Provides-Extra: docs
Requires-Dist: sphinx ; extra == 'docs'
Requires-Dist: sphinx-book-theme ; extra == 'docs'
Requires-Dist: myst-nb ; extra == 'docs'
Requires-Dist: ipywidgets ; extra == 'docs'
Requires-Dist: sphinx-new-tab-link !=0.2.2 ; extra == 'docs'
